ahead/__init__.py
ahead/config.py
ahead/ARMAGARCH/ArmaGarch.py
ahead/ARMAGARCH/__init__.py
ahead/Base/Base.py
ahead/Base/__init__.py
ahead/Basic/BasicForecaster.py
ahead/Basic/__init__.py
ahead/DynamicRegressor/DynamicRegressor.py
ahead/DynamicRegressor/__init__.py
ahead/EAT/EAT.py
ahead/EAT/__init__.py
ahead/FitForecast/FitForecasting.py
ahead/FitForecast/__init__.py
ahead/MLARCH/__init__.py
ahead/MLARCH/mlarch.py
ahead/Ridge2/Ridge2Regressor.py
ahead/Ridge2/__init__.py
ahead/VAR/VAR.py
ahead/VAR/__init__.py
ahead/utils/__init__.py
ahead/utils/multivariate.py
ahead/utils/tscv_indices.py
ahead/utils/unimultivariate.py
ahead/utils/univariate.py
ahead-0.22.0.dist-info/AUTHORS.rst
ahead-0.22.0.dist-info/LICENSE
ahead-0.22.0.dist-info/METADATA
ahead-0.22.0.dist-info/WHEEL
ahead-0.22.0.dist-info/top_level.txt
ahead-0.22.0.dist-info/RECORD
