Metadata-Version: 2.1
Name: ahead
Version: 0.22.0
Summary: Time series forecasting with Machine Learning and uncertainty quantification
Home-page: UNKNOWN
Author: T. Moudiki
Author-email: thierry.moudiki@gmail.com
License: BSD3 Clause Clear
Platform: UNKNOWN
Classifier: Development Status :: 3 - Alpha
Classifier: Intended Audience :: Developers
Classifier: Programming Language :: Python :: 3
Requires-Python: >=3.8
License-File: LICENSE
License-File: AUTHORS.rst
Requires-Dist: matplotlib
Requires-Dist: numpy
Requires-Dist: pandas
Requires-Dist: rpy2
Requires-Dist: scikit-learn
Requires-Dist: scipy
